mic_toolkit/__init__.py
mic_toolkit/synthetic/__init__.py
mic_toolkit/synthetic/generation.py
mic_toolkit/utils.py
mic_toolkit-0.3.1.dist-info/LICENSE
mic_toolkit-0.3.1.dist-info/METADATA
mic_toolkit-0.3.1.dist-info/WHEEL
mic_toolkit-0.3.1.dist-info/RECORD
