Metadata-Version: 2.1
Name: mic-toolkit
Version: 0.3.1
Summary: Simple synthetic data generation using LLMs.
License: MIT
Author: Ameen Shaikh
Author-email: mohammedameen9011@gmail.com
Requires-Python: >=3.12,<4.0
Classifier: License :: OSI Approved :: MIT License
Classifier: Programming Language :: Python :: 3
Classifier: Programming Language :: Python :: 3.12
Classifier: Programming Language :: Python :: 3.13
Requires-Dist: datasets (>=3.0.0,<4.0.0)
Requires-Dist: ollama (>=0.3.3,<0.4.0)
Requires-Dist: tqdm (>=4.67.0,<5.0.0)
